ezbak/__init__.py
ezbak/app.py
ezbak/cli.py
ezbak/constants.py
ezbak/entrypoint.py
ezbak/cli_commands/__init__.py
ezbak/cli_commands/create.py
ezbak/cli_commands/list.py
ezbak/cli_commands/prune.py
ezbak/cli_commands/restore.py
ezbak/controllers/__init__.py
ezbak/controllers/aws.py
ezbak/controllers/backup_manager.py
ezbak/controllers/retention_policy_manager.py
ezbak/models/__init__.py
ezbak/models/backup.py
ezbak/models/settings.py
ezbak/models/storage_location.py
ezbak/utils/__init__.py
ezbak/utils/helpers.py
ezbak/utils/validators.py
ezbak-0.12.0.dist-info/METADATA
ezbak-0.12.0.dist-info/WHEEL
ezbak-0.12.0.dist-info/entry_points.txt
ezbak-0.12.0.dist-info/licenses/LICENSE
ezbak-0.12.0.dist-info/RECORD
