Metadata-Version: 2.4
Name: ezbak
Version: 0.12.0
Summary: A simple tool to backup and restore data as tgz files.
Project-URL: Homepage, https://github.com/natelandau/ezbak
Project-URL: Repository, https://github.com/natelandau/ezbak
Author-email: Nate Landau <github@natelandau.com>
License-Expression: MIT
License-File: LICENSE
Classifier: License :: OSI Approved :: MIT License
Classifier: Programming Language :: Python :: 3.11
Classifier: Programming Language :: Python :: 3.12
Classifier: Programming Language :: Python :: 3.13
Classifier: Programming Language :: Python :: 3.14
Requires-Python: <3.15,>=3.11
Requires-Dist: apscheduler<4.0.0,>=3.11.2
Requires-Dist: boto3>=1.42.16
Requires-Dist: cappa>=0.31.0
Requires-Dist: nclutils>=2.1.0
Requires-Dist: pydantic-settings<3.0.0,>=2.10.1
Requires-Dist: pydantic<3.0.0,>=2.11.7
Requires-Dist: rich>=14.1.0
Requires-Dist: whenever>=0.9.4
